setup.py
kubefuse/__init__.py
kubefuse/cache.py
kubefuse/client.py
kubefuse/filesystem.py
kubefuse/kubefuse.py
kubefuse/path.py
kubefuse.egg-info/PKG-INFO
kubefuse.egg-info/SOURCES.txt
kubefuse.egg-info/dependency_links.txt
kubefuse.egg-info/entry_points.txt
kubefuse.egg-info/requires.txt
kubefuse.egg-info/top_level.txt
tests/__init__.py
tests/test_cache.py
tests/test_client.py
tests/test_filesystem.py
tests/test_path.py