Metadata-Version: 1.1
Name: kubefuse
Version: 0.7.2
Summary: A FUSE file system for Kubernetes
Home-page: https://github.com/bspaans/kubefuse
Author: Bart Spaans
Author-email: bart.spaans@gmail.com
License: Apache License v2
Platform: UNKNOWN
Classifier: Programming Language :: Python
Classifier: License :: OSI Approved :: Apache Software License
Classifier: Topic :: System
Classifier: Topic :: System :: Clustering
Classifier: Topic :: System :: Filesystems
